[
    {
        "nom" : "Chaussure Ozweego",
        "marque" : "Adidas",
        "type" : "Chaussures",
        "prix" : 129.95,
        "rating" : 4.0,
        "numReviews" : 15,
        "countInStock" : 12
    },
    {
        "nom" : "Chaussure Stan Smith",
        "marque" : "Adidas",
        "type" : "Chaussures",
        "prix" : 100,
        "rating" : 4.0,
        "numReviews" : 15,
        "countInStock" : 12
    },
    {
        "nom" : "Nike Air Max Plus I",
        "marque" : "Nike",
        "type" : "Chaussures",
        "prix" : 120,
        "rating" : 4.0,
        "numReviews" : 15,
        "countInStock" : 12
    },
    {
        "nom" : "Nike Air Max Plus II",
        "marque" : "Nike",
        "type" : "Chaussures",
        "prix" : 150,
        "rating" : 4.0,
        "numReviews" : 15,
        "countInStock" : 12
    },
    {
        "nom" : "Nike Air Max Plus III",
        "marque" : "Nike",
        "type" : "Chaussures",
        "prix" : 200,
        "rating" : 4.0,
        "numReviews" : 15,
        "countInStock" : 12
    },
    {
        "nom" : "Nike Air Zoom Pegasus",
        "marque" : "Nike",
        "type" : "Chaussures",
        "prix" : 125,
        "rating" : 4.0,
        "numReviews" : 15,
        "countInStock" : 12
    },
    
    {
        "nom" : "Sweat-Shirt Pinwheel Hooded",
        "marque" : "Adidas",
        "type" : "Vetement",
        "prix" : 64.95,
        "rating" : 4.0,
        "numReviews" : 15,
        "countInStock" : 12
    },
    {
        "nom" : "Veste d'hiver",
        "marque" : "Adidas",
        "type" : "Vetement",
        "prix" : 129.95,
        "rating" : 4.0,
        "numReviews" : 15,
        "countInStock" : 12
    },
    {
        "nom" : "Veste de survêtement",
        "marque" : "Adidas",
        "type" : "Vetement",
        "prix" : 85.95,
        "rating" : 4.0,
        "numReviews" : 15,
        "countInStock" : 12
    },
    {
        "nom" : "Sac a dos 4ATHLS",
        "marque" : "Adidas",
        "type" : "Accessoires",
        "prix" : 39.95,
        "rating" : 4.0,
        "numReviews" : 15,
        "countInStock" : 12
    },
    {
        "nom" : "Sac a dos classic",
        "marque" : "Adidas",
        "type" : "Vetement",
        "prix" : 24.95,
        "rating" : 4.0,
        "numReviews" : 15,
        "countInStock" : 12
    },
    {
        "nom" : "Sweat a capuche en tissu Fleece",
        "marque" : "Nike",
        "type" : "Vetement",
        "prix" : 70,
        "rating" : 4.0,
        "numReviews" : 15,
        "countInStock" : 12
    },
    {
        "nom" : "Casquette réglable",
        "marque" : "Nike",
        "type" : "Accessoires",
        "prix" : 30,
        "rating" : 4.0,
        "numReviews" : 15,
        "countInStock" : 12
    },
    {
        "nom" : "Pantalon pour Homme",
        "marque" : "Nike",
        "type" : "Vetement",
        "prix" : 65,
        "rating" : 4.0,
        "numReviews" : 15,
        "countInStock" : 12
    },
    {
        "nom" : "Ballon de football",
        "marque" : "Nike",
        "type" : "Accessoires",
        "prix" : 20,
        "rating" : 4.0,
        "numReviews" : 15,
        "countInStock" : 12
    }




]